[
  {
    "id": 50,
    "company": {
      "id": 15,
      "name": "METZ SPECIALITY MATERIALS"
    },
    "image": "products/METZ SPECIALITY MATERIALS/METZ_SICODUR_GRIGIO.jpg",
    "featured": false,
    "active": false,
    "timestamp": "2024-02-19T01:41:50.591588+00:00",
    "last_update": "2024-03-27T02:56:04.316968+00:00",
    "created_by": {
      "id": 110,
      "email": "matthew@metztiles.com.au"
    },
    "updated_by": {
      "id": 110,
      "email": "matthew@metztiles.com.au"
    },
    "user_role": "Distributor",
    "manufacturer_name": "CIPA GRES",
    "product_name": "Metz Sicodur® 200X200X12Mm R12 / P5",
    "product_code": "CI8818",
    "product_description": "FULL BODY PORCELAIN FLOOR TILE",
    "product_categories": [
      {
        "id": 3,
        "category_name": "Internal Wall Linings, finishes and partition systems"
      }
    ],
    "standard_dimensions": "200x200x12mm",
    "price_per_unit": 69.0,
    "product_functional_unit": "m2",
    "price_adjustment_structure": null,
    "lead_time": "4 weeks",
    "factory_location": null,
    "sustainability_rating": null,
    "environmental_impact": null,
    "certifications": [],
    "technical_specifications": null,
    "availability": null,
    "minimum_order_quantity": null,
    "maximum_order_quantity": null,
    "shipping_restrictions": null,
    "warranty_period": null,
    "maintenance_requirements": null,
    "installation_requirements": null,
    "compatibility_notes": null,
    "alternative_products": null,
    "related_products": null,
    "tags": null,
    "notes": null,
    "carbon_neutral": null,
    "carbon_offset_included": null,
    "carbon_offsets": null,
    "carbon_functional_unit": null,
    "embodied_energy": null,
    "embodied_energy_provided": null,
    "embodied_water_content": null,
    "embodied_water_content_provided": null,
    "net_carbon_emissions": null,
    "upfront_carbon_emissions": null,
    "upfront_carbon_assessment": null,
    "recyclable_percentage": null,
    "recyclable_percentage_description": "",
    "recyclable_offcuts": null,
    "recyclable_offcuts_description": "",
    "recycled_content_percentage": null,
    "recycled_content_description": "",
    "recycling_process_description": "",
    "recycling_process_locally_possible": null,
    "compostable_percentage": null,
    "compostable_conditions": "",
    "biodegradable_percentage": null,
    "biodegradable_conditions": "",
    "reusable": null,
    "reusable_description": "",
    "end_of_life_program": null,
    "end_of_life_program_description": "",
    "water_reduction_techniques": "",
    "transport_emissions_minimisation_techniques": "",
    "minimisation_design_strategy": "",
    "modern_slavery_assessment_complete": null,
    "modern_slavery_action_plan_complete": null,
    "modern_slavery_action_plan_comment": "",
    "modern_slavery_comments": "",
    "modern_slavery_incidents": null,
    "modern_slavery_link": null,
    "human_rights_assessment_complete": null,
    "detailed_certifications": [],
    "certifier_name": null,
    "risk_of_harm_posed": null,
    "risk_of_harm_posed_description": "",
    "installation_risks": "Yes",
    "installation_risks_description": "Contains Silicas",
    "substances_of_concern": null,
    "substances_of_concern_description": "",
    "volatile_organic_compounds": null,
    "volatile_organic_compounds_evidence": null,
    "volatile_organic_compounds_link": null,
    "expected_lifespan_years": 20,
    "manufacturers_warranty_years": 5,
    "factory_finished": true,
    "factory_finished_description": "grip",
    "manufacturing_locations": [],
    "material_locations": [],
    "storage_locations": [
      {
        "id": 149,
        "location_name": "Sydney NSW, Australia",
        "location_lat": -33.86882,
        "location_lon": 151.209296,
        "location_state": " Australia",
        "location_city": "Sydney NSW"
      }
    ],
    "specific_installation": null,
    "specific_installation_methods": "",
    "applied_finish_required": false,
    "applied_finish_required_description": "",
    "section_A_score": 60,
    "section_B_score": 0,
    "section_C_score": 33,
    "section_D_score": 25,
    "section_E_score": 0,
    "section_F_score": 67,
    "section_G_score": 0,
    "responsible_products_rating": null,
    "independent_lca": null,
    "independent_lca_link": null,
    "independent_lca_scope": null,
    "incomplete_details": "",
    "other_comments": "",
    "disclaimer_agreement": false,
    "compliance_requirements": [
      {
        "id": 114,
        "requirement": "Slip Rating",
        "file": "https://architectsdeclareapp.s3.amazonaws.com/media/products/METZ%20SPECIALITY%20MATERIALS/METZ%20SICODUR%C2%AE%20200X200X12MM%20R12%20/%20P5/compliance/R26604_iz7kW2G.pdf",
        "link": "",
        "rating": null
      }
    ],
    "type_of_packaging": "",
    "files": []
  }
]